ruff_score/__init__.py
ruff_score/__main__.py
ruff_score/cli.py
ruff_score/scorer.py
ruff_score-0.1.1.dist-info/METADATA
ruff_score-0.1.1.dist-info/WHEEL
ruff_score-0.1.1.dist-info/entry_points.txt
ruff_score-0.1.1.dist-info/licenses/LICENSE.md
ruff_score-0.1.1.dist-info/RECORD
