Metadata-Version: 2.4
Name: ruff-score
Version: 0.1.1
Summary: A Pylint-style scoring system for Ruff linter output
Project-URL: Homepage, https://github.com/AISHIK999/ruff-score
Project-URL: Repository, https://github.com/AISHIK999/ruff-score
Project-URL: Issues, https://github.com/AISHIK999/ruff-score/issues
Author-email: Aishik Mukherjee <aishikm2002@gmail.com>
License: MIT
License-File: LICENSE.md
Keywords: code-quality,linter,pylint,ruff,scoring
Classifier: Development Status :: 4 - Beta
Classifier: Intended Audience :: Developers
Classifier: License :: OSI Approved :: MIT License
Classifier: Programming Language :: Python :: 3
Classifier: Programming Language :: Python :: 3.8
Classifier: Programming Language :: Python :: 3.9
Classifier: Programming Language :: Python :: 3.10
Classifier: Programming Language :: Python :: 3.11
Classifier: Programming Language :: Python :: 3.12
Classifier: Programming Language :: Python :: 3.13
Classifier: Topic :: Software Development :: Libraries :: Python Modules
Classifier: Topic :: Software Development :: Quality Assurance
Requires-Python: >=3.8
Requires-Dist: ruff>=0.12.0
